RandomFileTree-1.2.0.data/scripts/randomfiletree
randomfiletree/__init__.py
randomfiletree/__main__.py
randomfiletree/cli.py
randomfiletree/core.py
randomfiletree/version.txt
randomfiletree/test/__init__.py
randomfiletree/test/test_cli.py
randomfiletree/test/test_core.py
RandomFileTree-1.2.0.dist-info/LICENSE.txt
RandomFileTree-1.2.0.dist-info/METADATA
RandomFileTree-1.2.0.dist-info/WHEEL
RandomFileTree-1.2.0.dist-info/top_level.txt
RandomFileTree-1.2.0.dist-info/RECORD
