Metadata-Version: 2.1
Name: RandomFileTree
Version: 1.2.0
Summary: Create a random file/directory tree/structure in python fortesting purposes.
Home-page: https://github.com/klieret/RandomFileTree
License: MIT
Project-URL: Bug Tracker, https://github.com/klieret/RandomFileTree/issues
Project-URL: Documentation, https://randomfiletree.readthedocs.io/
Project-URL: Source Code, https://github.com/klieret/RandomFileTree/
Keywords: testing,filetree,tree
Platform: UNKNOWN
Classifier: Programming Language :: Python :: 3
Classifier: License :: OSI Approved :: MIT License
Classifier: Operating System :: OS Independent
Classifier: Topic :: Utilities
